{
  "song_lyrics": [
    "Bhakti taṇā jyā pūr umaṭyā, koīnī parvā nathī,",
    "Mahāsamarth jyā gurujī maḷiyā, loknī parvā nathī...",
    "Ghanshyām Prabhu to bālvaymā, gharbār chhoḍī nīsaryā,",
    "Kathaṇ tap bahu ādaryā chhe, dehnī parvā tyajī... 1",
    "Bhagatjīe shirsāte, Swāmī Shrījī sevīyā,",
    "Gnān Guṇātīt pachyā pachhī, bījā gnānnī parvā nathī... 2",
    "Swāmījīe bālvaymā, bhekh preme grahaṇ karyo,",
    "Vruddh chhatā paṇ dinrāt vichare, dehnī parvā tyajī... 3",
    "Adharme jatā ugārīne, lākho satsangīo karyā,",
    "Ghaṇu jīvo e guru amārā, dehnī parvā nathī... 4",
    "Yogī Prabhunā dhyānmā, almast thaī Gondaḷ vase,",
    "Jaḍbharat jevī dashā chhe, loknī parvā nathī... 5",
    "Dās Rasik nit jhankhto, Swāmī Shrījī dayā karo,",
    "Sansār sāgar tarī jāshu, pachhī māyā taṇī parvā nathī... 6"
  ],
  "title": "Bhakti taṇā jyā pūr umaṭyā koīnī parvā nathī",
  "metadata": {
    "kirtan_info": "<div class=\"kirtan_info\" id=\"kirtan-info_en\">\n<p class=\"no_info_en\">1-944: Rasikdas</p>\n<p class=\"no_info_en\">Category: Shastriji Maharajna Pad</p>\n</div>",
    "media_info": {}
  },
  "part": 1,
  "no": 944
}