{
  "song_lyrics": [
    "Bhāgya baḍe jahā sant padhāre...",
    "Ye santan hai par upkārī, sharaṇ āyko leṭ ubārī 1",
    "Āvat santko ādar dīje, charaṇ dhoī charaṇāmrut līje 2",
    "Sāhabka ghar santan māhī, sant sāhab kachhu antar nāhī 3",
    "Kah hī Kabīr bhale sant padhāre, yug yugan ke kāj sudhāre 4"
  ],
  "title": "Bhāgya baḍe jahā sant padhāre",
  "metadata": {
    "kirtan_info": "<div class=\"kirtan_info\" id=\"kirtan-info_en\">\n<p class=\"no_info_en\">1-749: Kabirdas</p>\n<p class=\"no_info_en\">Category: Sant Mahima Pad</p>\n<p class=\"raag_info_en\"><a href=\"#\" onclick=\"showRaagDetails('en','3debe82e61223cb0207241c6f9a3dac4');return false\" title=\"Click for more details about raag\">Raag(s): Darbãri Kãnadã</a></p>\n<div id=\"raag_details_en\"></div>\n</div>",
    "media_info": {}
  },
  "part": 1,
  "no": 749
}