{
  "song_lyrics": [
    "Guru guru kahat sansārā, aise jag bharmāyā hai;",
    "Guru jagat me bahut kahāye, tākā bhed na pāyā hai...",
    "Mātpitā pratham guru jāno, dūjā dāī kahāyā hai;",
    "Tijā guru, tāhīku jāno, jinne nām dharāyā hai 1",
    "Chothā guru jehi vidyā dīnā, Akshar gnān sikhāyā hai;",
    "Mālā diyā so guru pānchmā, jehiHari nām†batāyā hai 2",
    "Chhatthā guru so sant kahāve, jin sab bharam miṭāyā hai;",
    "Sarjanhār so guru sātmā, āpe hī āp lakhāyā hai 3",
    "Aise guru binā bhavjal ko pār kou nahi pāyā hai;",
    "Brahmānand achal sadguru ke charan kamal lapṭāyā hai 4"
  ],
  "title": "Guru guru kahat sansārā aise jag bharmāyā hai",
  "metadata": {
    "kirtan_info": "<div class=\"kirtan_info\" id=\"kirtan-info_en\">\n<p class=\"no_info_en\">2-25: Sadguru Brahmanand Swami</p>\n<p class=\"no_info_en\">Category: Shri Harina Pad</p>\n</div>",
    "media_info": {}
  },
  "part": 2,
  "no": 25
}