{
  "song_lyrics": [
    "Gāvo gāvo re guṇ pragaṭ Prabhujīnā,",
    "Avsar nahi maḷe āvo re...",
    "Avsar nahi maḷe amūlakh āvo,",
    "Jīvan bhaktimā vitāvo re... gāvo 1",
    "Devone durlabh chhe darshan jenā,",
    "Swarūp sāchu samjāvo re... gāvo 2",
    "Tanḍā ne mandāṇā tāpone ṭāḷvā,",
    "Sadgurū charaṇomā jāvo re... gāvo 3",
    "Het karone tame Hari harijanmā,",
    "Āve nahi bhaktono abhāvo re... gāvo 4",
    "Pal ek vīte nahī Shrījī smaraṇ vinā,",
    "Mūrtimā manḍu lagāvo re... gāvo 5",
    "Vallabhdās kahe Yogījī amne,",
    "Bhān jagatnu bhulāvo re... gāvo 6"
  ],
  "title": "Gāvo gāvo re guṇ pragaṭ Prabhujīnā",
  "metadata": {
    "kirtan_info": "<div class=\"kirtan_info\" id=\"kirtan-info_en\">\n<p class=\"no_info_en\">1-636: Vallabhdas</p>\n<p class=\"no_info_en\">Category: Prapti ne Mahimana Pad</p>\n</div>",
    "media_info": {}
  },
  "part": 1,
  "no": 636
}