{
  "song_lyrics": [
    "Jaysi ramanīya kamanīya damanīya ari,",
    "Jaysi Sahajānand Akṣharvāsī... Jay° ṭek",
    "Tvamapi mam jīvanam tvamapi mam lochanam,",
    "tvamapi me vānchhit varad dāsī... Jay° 1",
    "Jay Shrīmanjul mṛudul madhur mukh vachan var,",
    "Jay Shrīchitvanī chalanī madhur hāsī;",
    "Jay Shrīkamalānan padmadal lochan,",
    "Karpad kamaldal tulya āsī... Jay° 2",
    "Jay Shrīsaundarya audāryavar guṇākar,",
    "Jaysi tvam saushīlya vātsalya rāshī;",
    "Jay Shrīkaruṇābhuvan jay Shrīkaruṇāghan,",
    "Jay Shrīkamalāraman Avināshī... Jay° 3",
    "Tvamasi bhajanīya namanīya shamanīya dukh,",
    "Tvamasi mam prāṇpati sukh prakāshī;",
    "Dehi mam Nāth tav sharaṇ rati achal mati,",
    "Premānand prāṇ kurbān jāshī... Jay° 4"
  ],
  "title": "Jaysi ramanīya kamanīya damanīya ari",
  "metadata": {
    "kirtan_info": "<div class=\"kirtan_info\" id=\"kirtan-info_en\">\n<p class=\"no_info_en\">1-26: Sadguru Premanand Swami</p>\n<p class=\"no_info_en\">Category: Prarthana</p>\n</div>",
    "media_info": {}
  },
  "part": 1,
  "no": 26
}