{
  "song_lyrics": [
    "Je Swāminārāyaṇ nām leshe, tenā badhā pātak bāḷī deshe;",
    "Chhe nām mārā shrutimā anek, sarvoparī ā ja ganāy ek. 1",
    "Jo Swāminārāyaṇ ek vār, rate bijā nām ratyā hajār;",
    "Japyā thakī je faḷ thāy tenu, karī shake varṇan koṇ enu. 2",
    "Shāḍaksharī mantra mahāsamarth, jethī thashe siddha samast arth;",
    "Sukhī kare sankat sarva kāpe, ante vaḷī Akshardhām āpe. 3",
    "Gāyatrīthī laksh gano vishesh, jāṇe ja jeno mahimā Mahesh;",
    "Jyā jyā mahā muktajano vasāy, ā kāḷmā to jap e ja thāy. 4",
    "Jo antkāḷe shravaṇe suṇāy, pāpī ghaṇo te paṇ moksha jāy;",
    "Te mantrathī bhūt pishāch bhāge, te mantrathī to sadbuddhi jāge. 5",
    "Te mantra jenā mukhthī japāy, tenā thakī to jam nāsi jāy;",
    "Shrī Swāminārāyaṇ je kaheshe, bhāve kubhāve paṇ mukti leshe. 6",
    "Shaḍaksharo chhe shaṭ shāstrasār, te to utāre bhavsindhu pār;",
    "Chhaye rutumā divase nishāye, sarve kriyāmā samaro sadāye. 7",
    "Pavitra dehe apavitra dehe, ā nām nitye smaravu sanehe;",
    "Jaḷe karīne tanmel jāy, ā nāmthī antar shuddh thāy. 8",
    "Jeṇe mahāpāp karyā anant, jeṇe pīdyā Brāhmaṇ dhenu sant;",
    "Te Swāminārāyaṇ nām letā, lājī mare chhe mukhthī kahetā. 9",
    "Shrī Swāminārāyaṇ nām sār, chhe pāpne te prajaḷāvnār;",
    "Pāpī ghaṇu antar hoy jenu, baḷyā viṇā kem rahe ja tenu.10"
  ],
  "title": "Je Swāminārāyaṇ nām leshe",
  "metadata": {
    "kirtan_info": "<div class=\"kirtan_info\" id=\"kirtan-info_en\">\n<p class=\"no_info_en\">1-156: <i>unknown</i></p>\n<p class=\"no_info_en\">Category: Nityavidhi - Nam Mahima</p>\n</div>",
    "media_info": {}
  },
  "part": 1,
  "no": 156
}