{
  "song_lyrics": [
    "Kar man Shrījī charanan par prīt,",
    "Shrījīcharan kar prīt pūraṇ, jāse hoy punīt...",
    "Jehī charan bhajī bhaye hai munivar, anant triguṇātīt,",
    "Tehī charan kar vās dradh, tab hoy jagme jīt... kar 1",
    "Mohvash hoy fīryo manvā tāme bhayo hai fajīt,",
    "Alp sukhkī āsh karke, bhayo ati bhaybhīt... kar 2",
    "Bhaje tāku bhajat Ghanshyām yehī anādi rīt,",
    "Muktānand kahe ab milyo hai, avsar mān lenā mīt... kar 3"
  ],
  "title": "Kar man Shrījī charanan par prīt",
  "metadata": {
    "kirtan_info": "<div class=\"kirtan_info\" id=\"kirtan-info_en\">\n<p class=\"no_info_en\">2-18: Sadguru Muktanand Swami</p>\n<p class=\"no_info_en\">Category: Shri Harina Pad</p>\n<p class=\"raag_info_en\"><a href=\"#\" onclick=\"showRaagDetails('en','b237d1135fbd142e1b2423820bb50675');return false\" title=\"Click for more details about raag\">Raag(s): Bhoopãli</a></p>\n<div id=\"raag_details_en\"></div>\n</div>",
    "media_info": {}
  },
  "part": 2,
  "no": 18
}