{
  "song_lyrics": [
    "Khammā mārā Yogī Mahārāj,",
    "Āngaṇe kyāre padhārsho;",
    "Ghaḍī ghaḍī jou tārī vāṭ,",
    "Āngaṇe kyāre padhārsho...",
    "Tamārī vāṭmā rojnā ujāgrā,",
    "Ānkhaḍīo āsuḍe bhīnjāy āngaṇe... 1",
    "Shraddhānā dīvḍā me to pragaṭāvyā,",
    "Fūlḍā verāvyā māre dvār āngaṇe... 2",
    "Kāl kerā vāydā kām nahi āve,",
    "Āvjo āj na āj āngaṇe... 3",
    "Āvyā Yogījī māre āngaṇīe,",
    "Darshan devāne kāj āngaṇe... 4"
  ],
  "title": "Khammā mārā Yogī Mahārāj",
  "metadata": {
    "kirtan_info": "<div class=\"kirtan_info\" id=\"kirtan-info_en\">\n<p class=\"no_info_en\">2-114: <i>unknown</i></p>\n<p class=\"no_info_en\">Category: Yogiji Maharajna Pad</p>\n</div>",
    "media_info": {}
  },
  "part": 2,
  "no": 114
}