{
  "song_lyrics": [
    "Māre āj Prītam gher āviyā jī re,",
    "Bharī thāḷ motīḍe vadhāviyā jī re...",
    "Pahelā nīr une te navrāviyā jī re,",
    "Pachhī Prītam mahī padhrāviyā jī re... māre āj 1",
    "Me to bhojan jamaḍyā bhātbhātnā jī re,",
    "Vahāle āpyā te sukh ekāntnā jī re... māre āj 2",
    "Pe’lu paraṭhyu hatu te veṇe paḷiyā jī re,",
    "Vā’lo hete karīne mujne maḷyā jī re... māre āj 3",
    "Brahmānand kahe dhanya ājnī ghaḍī jī re,",
    "Māro vahālojī padhāryā sejḍī jī re... māre āj 4"
  ],
  "title": "Māre āj Prītam gher āviyā jī re",
  "metadata": {
    "kirtan_info": "<div class=\"kirtan_info\" id=\"kirtan-info_en\">\n<p class=\"no_info_en\">1-779: Sadguru Brahmanand Swami</p>\n<p class=\"no_info_en\">Category: Leelana Pad</p>\n</div>",
    "media_info": {}
  },
  "part": 1,
  "no": 779
}