{
  "song_lyrics": [
    "Navīn-megh-sannibham sunīl-kamal-rachhavim",
    "Suhāsar-njitādharam namāmi Kṛuṣhṇasundaram... 1",
    "Yashoda-Nand-Nandanam sureṇ-pād-vandanam",
    "Suvarṇ-ratna-maṇḍanam namāmi Kṛuṣhṇasundaram... 2",
    "Bhavābdhi-karṇa-dhārakam bhayābdhi-nāsh-kārakam",
    "Mumukṣhu-muktidāyakam namāmi Kṛuṣhṇasundaram... 3"
  ],
  "title": "Navīn-megh-sannibham sunīl-kamal-rachhavim",
  "metadata": {
    "kirtan_info": "<div class=\"kirtan_info\" id=\"kirtan-info_en\">\n<p class=\"no_info_en\">2-332: <i>unknown</i></p>\n<p class=\"no_info_en\">Category: Mantra-Stotra</p>\n</div>",
    "media_info": {}
  },
  "part": 2,
  "no": 332
}