{
  "song_lyrics": [
    "Re sundarvar bolyā Shyām, kahe chhe vā’lo potānu dhām... Re sundar° ṭek",
    "Re bhinna-bhinna ākāsh rachāye, re jujavo shabda temā thāye;",
    "Tem ja sahumā ved mune gāye... Re sundar° 1",
    "Re Akṣhar shakti ghaṇī sārī, re brahmānḍ pratye nyārī nyārī;",
    "Temā sahu mūrtio mārī... Re sundar° 2",
    "Re Akṣhar anant kaḷā dhāre, re agaṇit rūp thāu tyāre;",
    "Mune jīv pāme eṇedvāre†... Re sundar° 3",
    "Re Akṣhar koṭino hu Swāmī, re mujmā rahe sahu lay pāmī;",
    "Shobhu sadā ek rūp dhāmī... Re sundar° 4",
    "Re satsangī sahu nar nārī, tam arathe āje deh dhārī;",
    "Premsakhī jāye balihārī... Re sundar° 5"
  ],
  "title": "Re sundarvar bolyā Shyām",
  "metadata": {
    "kirtan_info": "<div class=\"kirtan_info\" id=\"kirtan-info_en\">\n<p class=\"no_info_en\">1-451: Sadguru Premanand Swami</p>\n<p class=\"no_info_en\">Category: Updeshna Pad</p>\n</div>",
    "media_info": {}
  },
  "part": 1,
  "no": 451
}