{
  "song_lyrics": [
    "Santnu swarūp dhārī Shrījī āj padhāryā re,",
    "Koṭī jīvonā kalyāṇ karavā, avanī upar āvyā re... °ṭek",
    "Akṣhardhāmthī kṛupā karīne, avanī upar āvyā,",
    "Sarvoparī niṣhṭhāne kāje Akṣhar Mukto lāvyā re... Sant° 1",
    "Gām Maheḷāve janma dharīne, bāḷa-charitro kīdhā,",
    "Māt pitāne sukh arpīne, pantha vairāgyanā līdhā re... Sant° 2",
    "Bāḷpaṇāmā dīkṣhā laīne, jap-tap ādi vrat ādariyā,",
    "Jīvaṇrangne guru karīne, shāstrādik to bhaṇiyā re... Sant° 3",
    "Bhagatjīne sevā karīne, rājī atishay kīdhā,",
    "Tav ichchhāne pūrṇa karīshu, evā kol ja dīdhā re... Sant° 4",
    "Ati alaukik dhām rachāvyā, shuddha upāsanā kāje,",
    "Mahā ekāntik dharma felāvavā, vicharī rahyā chho āje re... Sant° 5",
    "Adham jīvone updesh āpī, bhakti kerā rang lagāvyā,",
    "Guṇātītnu gnān ja daīne, jīvan-mukta banāvyā re... Sant° 6",
    "Bole ḍole roj Swāmījī, nit nit parachā āpe,",
    "Nij bhaktone sukh arpīne, bhav-bandhan dukh kāpe re... Sant° 7",
    "Dās Chhagan kahe Prabhu bhajvāno, nahi maḷe avsar āvo,",
    "Pragaṭ Harinī bhakti karīne, laī lyo anupam lhāvo re... Sant° 8"
  ],
  "title": "Santnu swarūp dhārī Shrījī āj padhāryā re",
  "metadata": {
    "kirtan_info": "<div class=\"kirtan_info\" id=\"kirtan-info_en\">\n<p class=\"no_info_en\">1-936: Chhagandas</p>\n<p class=\"no_info_en\">Category: Shastriji Maharajna Pad</p>\n</div>",
    "media_info": {}
  },
  "part": 1,
  "no": 936
}