{
  "song_lyrics": [
    "Shobhānā shaṇgār Hari, mārā haiyānā chho hār vahālā;",
    "Dharmataṇā kumār mārā, prāṇ taṇā ādhār vahālā° 1",
    "Atishe rūpāḷā sundar, shikhānā chhe kesh vahālā;",
    "Chhabī upar balhārī jāye, shārad ne sheṣh vahālā° 2",
    "Shikhāne samīpe rūḍo, ek til āge vahālā;",
    "E chhabī nīrakhtā mārā, sarave dukh bhāge vahālā° 3",
    "Shikhāne pachhvāḍe jamṇī, kore te kahīe vahālā;",
    "Traṇ til chhe ati rūḍā, sāmu joīne rahīe vahālā° 4",
    "Nakhshikh nīrkhī sundar sarve, chihna me gāyā vahālā;",
    "Chintvan karī nitye mārā, chittamā ṭherāyā vahālā° 5",
    "Bāvan chhe sarve chihna, tresaṭh til chhe jo vahālā;",
    "Rūp shīl ne guṇe sotā, antarmā rahejo vahālā° 6",
    "E vinā zīṇā til chihna chhe, angmā apār vahālā;",
    "Gāyā me to joī mārī, buddhine anusār vahālā° 7",
    "Āvī rīte mūratine je, antarmā dhāre vahālā;",
    "Prīt karīne chihna anupam, sarve sambhāre vahālā° 8",
    "Tenā urmā āvī tame, Nāth karo vās vahālā;",
    "Kām krodh ne kāḷ māyā, te sahu pāme nāsh vahālā° 9",
    "E pad je koī shīkhe suṇe, prīt karīne gāshe vahālā;",
    "Premānand kahe te par Swāmī, bahu rājī thāshe vahālā° 10"
  ],
  "title": "Shobhānā shaṇgār Hari",
  "metadata": {
    "kirtan_info": "<div class=\"kirtan_info\" id=\"kirtan-info_en\">\n<p class=\"no_info_en\">1-327: Sadguru Premanand Swami</p>\n<p class=\"no_info_en\">Category: Murtina Pad</p>\n</div>",
    "media_info": {}
  },
  "part": 1,
  "no": 327
}