{
  "song_lyrics": [
    "Vahetu jīvan tamāru Gangānī dhārā,",
    "Ghaṇu re jīvo Pramukhjī prāṇ chho amārā...",
    "Bhaktimā līn ahonish brahmaras vahāvatā,",
    "Mukhmā chhe nām Harinu karmā japmāḷā... Ghaṇu",
    "Swāmī tuj pagale pagale pragaṭe ajavāḷā,",
    "Bhavmā būḍatā jīvone tame zālnārā... Ghaṇu",
    "Māyānu bandhan kāpī ātam oḷakhāvajo,",
    "Dehbhāv doṣho saghaḷā tame ṭāḷnārā... Ghaṇu",
    "Antkāḷe āvī Swāmī amane ugārjo,",
    "Akṣharrūp karajo Harinā khoḷe khelnārā... Ghaṇu"
  ],
  "title": "Vahetu jīvan tamāru Gangānī dhārā",
  "metadata": {
    "kirtan_info": "<div class=\"kirtan_info\" id=\"kirtan-info_en\">\n<p class=\"no_info_en\">2-3046: Sadhu Aksharjivandas</p>\n<p class=\"no_info_en\">Category: Pramukh Swami Maharajna Pad</p>\n</div>",
    "media_info": {}
  },
  "part": 2,
  "no": 3046
}