{
  "song_lyrics": [
    "Āvo mārā Mohan mīṭhḍā lāl, ke jou tārī mūrti re lol;",
    "Jatan karī rākhu rasiyā rāj, visāru nahi urthī re lol... 1",
    "Man māru mohyu Mohanlāl, pāghalḍīnī bhātmā re lol;",
    "Āvo orā chhogalā khosu chhel, khāntilā jou khāntmā re lol... 2",
    "Vahālā tāru jhaḷke sundar bhāl, tilak rūḍā karyā re lol;",
    "Vahālā tārā vām karaṇmā til, tene manḍā haryā re lol... 3",
    "Vahālā tārī bhrakuṭine bāṇe Shyām, kāḷaj mārā koriyā re lol;",
    "Neṇe tāre Premsakhīnā Nāth, ke chitt mārā choriyā re lol... 4"
  ],
  "title": "Āvo mārā Mohan mīṭhaḍā lāl",
  "metadata": {
    "kirtan_info": "<div class=\"kirtan_info\" id=\"kirtan-info_en\">\n<p class=\"no_info_en\">1-186: Sadguru Premanand Swami</p>\n<p class=\"no_info_en\">Category: Dhyan Chintamani</p>\n</div>",
    "media_info": {}
  },
  "part": 1,
  "no": 186
}