{
  "song_lyrics": [
    "Ek ja chho Swāmī tame sahuno sahāro,",
    "Chārekor bharyo bhavsāgar ā khāro... °ṭek",
    "Jīvandorī chho Swāmī āp amārī,",
    "Rākho tem raheshu jāṇī marjī tamārī,",
    "Ḍūbtī ā naiyāne āpjo othāro,",
    "Chāre kor bharyo bhavsāgar ā khāro... Ek ja chho° 1",
    "Āshā sarve chhoḍī doḍī sharaṇmā āvyo,",
    "Bhūlthī bharel chhatā āpe apnāvyo,",
    "Hetthī bolāvo Bāpā bāḷ chhu tamāro,",
    "Chāre kor bharyo bhavsāgar ā khāro... Ek ja chho° 2",
    "Jagāḍī prīt prāṇjīvan nibhāvjo,",
    "Antsame Shrījī-Swāmī velāvelā āvajo,",
    "Vanmāḷīdāsnī vinantī svīkāro,",
    "Chāre kor bharyo bhavsāgar ā khāro... Ek ja chho° 3"
  ],
  "title": "Ek ja chho Swāmī tame sahuno sahāro",
  "metadata": {
    "kirtan_info": "<div class=\"kirtan_info\" id=\"kirtan-info_en\">\n<p class=\"no_info_en\">2-3001: Vanmalidas</p>\n<p class=\"no_info_en\">Category: Pramukh Swami Maharajna Pad</p>\n</div>",
    "media_info": {}
  },
  "part": 2,
  "no": 3001
}