{
  "song_lyrics": [
    "Gunsāgar Ghanshyāmjī sukhsāgar jehī nām,",
    "Japat nām nar pātkī hot hai pūran kām...",
    "Bhuvi rajkan kou gine barkhā bund gināy,",
    "Tārankī ginatī kare pan Harigun gineu na jāy... gun 1",
    "Charitra kiye Mahārājne avni upar āy,",
    "Likhte hārī shārdā sahasra badan nit gāy... gun 2",
    "Chyār baran āshram chau pashu pakshī parjant,",
    "Bhut pret ādi sabe tāre jīva anant... gun 3",
    "Daras paras deke Hari fal jal patra le hār,",
    "Premānand kiye Nāthne anant jīva bhavpār... gun 4"
  ],
  "title": "Gunsāgar Ghanshyāmjī sukhsāgar jehī nām",
  "metadata": {
    "kirtan_info": "<div class=\"kirtan_info\" id=\"kirtan-info_en\">\n<p class=\"no_info_en\">1-673: Sadguru Premanand Swami</p>\n<p class=\"no_info_en\">Category: Prapti ne Mahimana Pad</p>\n</div>",
    "media_info": {}
  },
  "part": 1,
  "no": 673
}