{
  "song_lyrics": [
    "Janunījīvo re Gopīchandnī,",
    "putrane preryo vairāg jī;",
    "Updesh āpyo eṇī pere,",
    "lāgyo sansārīḍo āg jī... jan 1",
    "Dhanya dhanya mātā Dhruv taṇī,",
    "kahyā kathaṇ vachan jī;",
    "Rāj sāj sukhparharī,",
    "vege chāliyā van jī... jan 2",
    "Bhalo re tyāg Bhartharī taṇo,",
    "tajī jene solse nār jī;",
    "Mandir jharūkhā melī karī,",
    "āsan kidhlā bā’r jī... jan 3",
    "Ūṭhī na shake re ūntiyo,",
    "bahu bolāvyo Bājand jī;",
    "Tene re dekhīne trās upanyo,",
    "līdhī fakīrī chhoḍyo fand jī... jan 4",
    "Evā vairāgya vantne jāu vārṇe,",
    "bījā gayā re anek jī;",
    "Bhalā re bhundā avnī upare,",
    "gaṇtā nāve chhek jī... jan 5",
    "Kyā gayu kuḷ Rāvaṇ taṇu,",
    "Sagar sut sāṭh hajār jī;",
    "Na rahyu nāṇu re rājā Nandnu,",
    "sarvesupanvyavhār jī... jan 6",
    "Evā chhatrāpati chālī gayā,",
    "rāj mūkī rājan jī;",
    "Dev dānav re mānav muni,",
    "sarve jāṇo supan jī... jan 7",
    "Samjī muko to sāru ghaṇu,",
    "jarūr mukāvshe Jam jī;",
    "Nishkuḷānand kahe nahi maṭe,",
    "sāchu kahu khāī sam jī... jan 8"
  ],
  "title": "Janunī jīvo re Gopīchandnī",
  "metadata": {
    "kirtan_info": "<div class=\"kirtan_info\" id=\"kirtan-info_en\">\n<p class=\"no_info_en\">1-478: Sadguru Nishkulanand Swami</p>\n<p class=\"no_info_en\">Category: Updeshna Pad</p>\n</div>",
    "media_info": {}
  },
  "part": 1,
  "no": 478
}