{
  "song_lyrics": [
    "Mai to tohīsu lagāyā ho nehrā;",
    "Merā sāvrā piyā, mere jīykā jīyā...",
    "Nehrā lagāy ke nain me rākhu;",
    "Vārī ḍārū tan man hojī gehrā... mai to 1",
    "Akhanḍ raho more nain ke āge;",
    "Barso bachan rahojī mehrā... mai to 2",
    "Nakhshikh nirakhu chakor chand jyu;",
    "Karī rākhu ur hojī tehrā... mai to 3",
    "Premānand kahe paherāvu prītsu;",
    "Gajrā gulābī ho shir sehrā... mai to 4"
  ],
  "title": "Mai to tohīsu lagāyā ho neharā",
  "metadata": {
    "kirtan_info": "<div class=\"kirtan_info\" id=\"kirtan-info_en\">\n<p class=\"no_info_en\">1-863: Sadguru Premanand Swami</p>\n<p class=\"no_info_en\">Category: Prakirna Pad</p>\n</div>",
    "media_info": {}
  },
  "part": 1,
  "no": 863
}