{
  "song_lyrics": [
    "Prāt thayu manmohan pyārā, Prītam shu rahyā poḍhīne;",
    "Vāramvār karu chhu vinati, Jagjīvan kar joḍīne... prāt 1",
    "Ghargharthī govāḷo āvyā, darshan kāraṇ doḍīne;",
    "Āngaṇiye ūbhī Vraj abaḷā, mahī valovā chhoḍīne... prāt 2",
    "Bahurūpi darvāje beṭhā, Shankar nejā khoḍīne;",
    "Mukhḍu jovā ātur manmā, jore rākhyā oḍīne... prāt 3",
    "Bhairav rāg guṇijan gāve, tān manohar toḍīne;",
    "Brahmānandnā Nāth Vihārī, ūṭho āḷas moḍīne... prāt 4"
  ],
  "title": "Prāt thayu manmohan pyārā",
  "metadata": {
    "kirtan_info": "<div class=\"kirtan_info\" id=\"kirtan-info_en\">\n<p class=\"no_info_en\">1-91: Sadguru Brahmanand Swami</p>\n<p class=\"no_info_en\">Category: Prabhatiya</p>\n</div>",
    "media_info": {}
  },
  "part": 1,
  "no": 91
}