{
  "song_lyrics": [
    "Rahanā nahī des birānā hai °ṭek",
    "Yah sansār kāgadkī puḍiyā, būnd paḍe ghul jānā hai° 1",
    "Yah sansār kānṭekī bāḍī, ulaz ulaz mari jānā hai° 2",
    "Yah sansār zāḍ au’ zānkhar, āg lage bari jānā hai° 3",
    "Kahat Kabīr suno bhāī sādho, satguru nām ṭhikānā hai° 4"
  ],
  "title": "Rahanā nahī des birānā hai",
  "metadata": {
    "kirtan_info": "<div class=\"kirtan_info\" id=\"kirtan-info_en\">\n<p class=\"no_info_en\">2-318: Kabirdas</p>\n<p class=\"no_info_en\">Category: Anya Hindi Pad</p>\n</div>",
    "media_info": {}
  },
  "part": 2,
  "no": 318
}