{
  "song_lyrics": [
    "Sukhdāyak re, sāchā santno sang,",
    "Sant samāgam kījīe...",
    "Jīre sant samāgamthī ṭaḷe, āshā trushṇā re,",
    "Īrshyā abhimān, moh matsar mamtā baḷe;",
    "Pragaṭe urmā re, Prabhunu dradh gnān... sant 1",
    "Jī re sant samāgamthī thayā, muni Nārad re,",
    "Harinu man āp, anek patit uddhāriyā;",
    "Tenā jashno re, moṭo partāp... sant 2",
    "Jī re siddha thayā satsangthī, Shuk ādik re,",
    "Munīvar sukh rūp, chitt chotyu Hari charaṇmā;",
    "Jāṇyo santthī re, moṭo maram anūp... sant 3",
    "Jī re mahimā moṭo chhe mahantno, jene seve re,",
    "Chhuṭe māyānu jāḷ, prīt vadhe Parabrahmamā;",
    "Muktānand kahe re, tajī āḷ pampāḷ... sant 4"
  ],
  "title": "Sukhdāyak re sāchā santno sang",
  "metadata": {
    "kirtan_info": "<div class=\"kirtan_info\" id=\"kirtan-info_en\">\n<p class=\"no_info_en\">1-706: Sadguru Muktanand Swami</p>\n<p class=\"no_info_en\">Category: Sant Mahima Pad</p>\n</div>",
    "media_info": {}
  },
  "part": 1,
  "no": 706
}