{
  "song_lyrics": [
    "Vandu Sahajānand rasrūp, anupam sārne re lol;",
    "Jene bhajtā chhuṭe fand, kare bhav pārne re lol... 1",
    "Samaru pragaṭ rūp Sukhdhām, anupam nāmne re lol;",
    "Jene bhav Brahmādik dev, bhaje tajī kāmne re lol... 2",
    "Je Hari Aksharbrahma ādhār, pār koī nav lahe re lol;",
    "Jene shesh sahasramukh gāy, nigam neti kahe re lol... 3",
    "Varṇavu sundar rūp anup, jugal charaṇe namī re lol;",
    "Nakhshikh Premsakhīnā Nāth, raho urmā ramī re lol... 4"
  ],
  "title": "Vandu Sahajānand rasrūp",
  "metadata": {
    "kirtan_info": "<div class=\"kirtan_info\" id=\"kirtan-info_en\">\n<p class=\"no_info_en\">1-185: Sadguru Premanand Swami</p>\n<p class=\"no_info_en\">Category: Dhyan Chintamani</p>\n</div>",
    "media_info": {}
  },
  "part": 1,
  "no": 185
}