{
  "song_lyrics": [
    "Āj to aṭārī men birāje avatārī āli,",
    "Rūp kī bisekatāī nek jāī dekh rī. 1",
    "Sānvaro sujān mukh chāvat hai pān āli,",
    "Mān men maror pāgh bāndhat vishekh rī. 2",
    "Gajarā gulābaun ke gūnthat gumānī nīke,",
    "Tīkhe tīkhe nain men arunatā kī rekh rī. 3",
    "Upamā kahī na jāye koṭi kām lāge pāye,",
    "Premānand āge gāye rīze naṭ bhekh rī. 4"
  ],
  "title": "Āj to aṭārī men birāje",
  "metadata": {
    "kirtan_info": "<div class=\"kirtan_info\" id=\"kirtan-info_en\">\n<p class=\"no_info_en\">2-1320: Sadguru Premanand Swami</p>\n<p class=\"no_info_en\">Category: Leelana Pad</p>\n<p class=\"raag_info_en\"><a href=\"#\" onclick=\"showRaagDetails('en','fa12cd5f94338451419c4c689e6c815a');return false\" title=\"Click for more details about raag\">Raag(s): Poorvi</a></p>\n<div id=\"raag_details_en\"></div>\n</div>",
    "media_info": {}
  },
  "part": 2,
  "no": 1320
}