{
  "song_lyrics": [
    "Āvnā mere manke meram, salūne Shyām re;",
    "Salūne Shyām re, mai samaru terā nām re... āvnā° ṭek",
    "Pahelī prīt lagāy ke,ab āsh karo mat dūr;†",
    "Dūr rahe dukh hot hai, mai tarat marungī zūr re... Meram° 1",
    "Darade dīvānī mai ḍolu, mere vrehakā bāḍhyā rog;",
    "Rogkī mārī rīsme, mai jāy pe’rungī jog re... Meram° 2",
    "Prītam ḍāryā premkā, tum jor gale bīch fand;",
    "Fandkī mārī mai firu, baljāvat Brahmānand re... Meram° 3"
  ],
  "title": "Āvnā mere manke meram salūne Shyām re",
  "metadata": {
    "kirtan_info": "<div class=\"kirtan_info\" id=\"kirtan-info_en\">\n<p class=\"no_info_en\">1-816: Sadguru Brahmanand Swami</p>\n<p class=\"no_info_en\">Category: Leelana Pad</p>\n</div>",
    "media_info": {}
  },
  "part": 1,
  "no": 816
}